image_filter/__init__.py
image_filter/custom_image_processor.py
image_filter_library_oss-1.1.2.dist-info/LICENSE
image_filter_library_oss-1.1.2.dist-info/METADATA
image_filter_library_oss-1.1.2.dist-info/WHEEL
image_filter_library_oss-1.1.2.dist-info/top_level.txt
image_filter_library_oss-1.1.2.dist-info/RECORD
