Metadata-Version: 2.1
Name: image_filter_library_oss
Version: 1.1.2
Summary: A library for processing BMP images
Home-page: https://github.com/kimmin9511/image_filter_project
Author: kimmin9511
Author-email: gimm50655@gmail.com
License: MIT
Classifier: Programming Language :: Python :: 3
Classifier: License :: OSI Approved :: MIT License
Classifier: Operating System :: OS Independent
Requires-Python: >=3.6
License-File: LICENSE
Requires-Dist: pillow
Requires-Dist: numpy
Requires-Dist: opencv-python
Requires-Dist: sphinx
Requires-Dist: sphinx-autodoc-typehints
